literate_sphinx.py
literate_sphinx-0.1.5.dist-info/licenses/LICENSES/BSD-2-Clause.txt
literate_sphinx-0.1.5.dist-info/WHEEL
literate_sphinx-0.1.5.dist-info/METADATA
literate_sphinx-0.1.5.dist-info/RECORD
