Metadata-Version: 2.4
Name: literate-sphinx
Version: 0.1.5
Summary: A literate programming extension for Sphinx
Keywords: sphinx,literate programming
Author-email: Hubert Chathi <hubert@uhoreg.ca>
Classifier: Development Status :: 3 - Alpha
Classifier: Framework :: Sphinx :: Extension
Classifier: Intended Audience :: Developers
Classifier: License :: OSI Approved :: BSD License
License-File: LICENSES/BSD-2-Clause.txt
Requires-Dist: sphinx
Requires-Dist: myst-parser ; extra == "build"
Requires-Dist: black ; extra == "lint"
Requires-Dist: types-docutils ; extra == "lint"
Requires-Dist: mypy ; extra == "lint"
Project-URL: Documentation, https://uhoreg.gitlab.io/literate-sphinx/
Project-URL: Home, https://gitlab.com/uhoreg/literate-sphinx/
Project-URL: Source, https://gitlab.com/uhoreg/literate-sphinx
Provides-Extra: build
Provides-Extra: lint
